[{"model": "proyecto.distrito", "pk": 1, "fields": {"distrito": "Matriz", "complete": true}}, {"model": "proyecto.distrito", "pk": 2, "fields": {"distrito": "Altamira", "complete": true}}, {"model": "proyecto.distrito", "pk": 3, "fields": {"distrito": "Planta Veracruz", "complete": true}}, {"model": "proyecto.distrito", "pk": 4, "fields": {"distrito": "Poza Rica", "complete": true}}, {"model": "proyecto.distrito", "pk": 5, "fields": {"distrito": "Villahermosa", "complete": true}}, {"model": "proyecto.distrito", "pk": 6, "fields": {"distrito": "Veracruz", "complete": true}}]